signpolicy/__init__.py
signpolicy/cli.py
signpolicy/main.py
signpolicy/utils.py
signpolicy-1.0.0.dist-info/licenses/LICENSE
signpolicy-1.0.0.dist-info/METADATA
signpolicy-1.0.0.dist-info/WHEEL
signpolicy-1.0.0.dist-info/entry_points.txt
signpolicy-1.0.0.dist-info/top_level.txt
signpolicy-1.0.0.dist-info/RECORD
