Metadata-Version: 2.4
Name: signpolicy
Version: 1.0.0
License-File: LICENSE
Requires-Dist: rich
Dynamic: license-file
